build/lib/build/lib/build/lib/ttcrypt/__init__.py
build/lib/build/lib/build/lib/ttcrypt/aes.py
build/lib/build/lib/build/lib/ttcrypt/cmd.py
build/lib/build/lib/ttcrypt/__init__.py
build/lib/build/lib/ttcrypt/aes.py
build/lib/build/lib/ttcrypt/cmd.py
build/lib/ttcrypt/__init__.py
build/lib/ttcrypt/aes.py
build/lib/ttcrypt/cmd.py
ttcrypt/__init__.py
ttcrypt/aes.py
ttcrypt/cmd.py
ttcrypto/__init__.py
ttcrypto/aes.py
ttcrypto/cmd.py
ttcrypto-0.1.dist-info/licenses/LICENSE.md
ttcrypto-0.1.dist-info/METADATA
ttcrypto-0.1.dist-info/WHEEL
ttcrypto-0.1.dist-info/entry_points.txt
ttcrypto-0.1.dist-info/top_level.txt
ttcrypto-0.1.dist-info/RECORD
