Metadata-Version: 2.4
Name: ttcrypto
Version: 0.1
Summary: Tools for encryption/decryption
Author-email: Dmitriy Vlasov <support@tamtamteam.com>
License: MIT
Keywords: cryptography,utils
Classifier: Development Status :: 5 - Production/Stable
Classifier: Environment :: Plugins
Classifier: Intended Audience :: Developers
Classifier: License :: OSI Approved :: Apache Software License
Classifier: Programming Language :: Python
Classifier: Programming Language :: Python :: 3
Classifier: Programming Language :: Python :: 3.10
Classifier: Programming Language :: Python :: 3.11
Classifier: Programming Language :: Python :: 3.12
Classifier: Programming Language :: Python :: 3.13
Classifier: Programming Language :: Python :: 3.14
Classifier: Topic :: Software Development :: Libraries :: Python Modules
Requires-Python: >=3.10
License-File: LICENSE.md
Requires-Dist: cryptography
Provides-Extra: dev
Requires-Dist: ttutils; extra == "dev"
Requires-Dist: pytest-runner; extra == "dev"
Requires-Dist: pytest; extra == "dev"
Requires-Dist: pytest-cov; extra == "dev"
Requires-Dist: pytest-asyncio; extra == "dev"
Requires-Dist: ruff; extra == "dev"
Requires-Dist: mypy; extra == "dev"
Dynamic: license-file
